jig/__init__.py
jig/analyzer/__init__.py
jig/analyzer/application/__init__.py
jig/analyzer/domain/__init__.py
jig/analyzer/domain/dependency/__init__.py
jig/analyzer/domain/dependency/import_dependency.py
jig/analyzer/domain/dependency/module_dependency.py
jig/cli/__init__.py
jig/cli/debug.py
jig/cli/interaction.py
jig/cli/main.py
jig/collector/__init__.py
jig/collector/application/__init__.py
jig/collector/domain/__init__.py
jig/collector/domain/ast/__init__.py
jig/collector/domain/source_code/__init__.py
jig/collector/domain/source_code/source_code.py
jig/collector/domain/source_code/source_code_collection.py
jig/collector/domain/source_code/source_code_import_dependency.py
jig/collector/domain/source_file/__init__.py
jig/collector/domain/source_file/source_file.py
jig/collector/domain/source_file/source_file_path.py
jig/collector/domain/values/__init__.py
jig/collector/domain/values/import_path.py
jig/collector/domain/values/import_path_collection.py
jig/collector/domain/values/module_path.py
jig/visualizer/__init__.py
jig/visualizer/application/__init__.py
jig/visualizer/domain/__init__.py
jig/visualizer/module_dependency/__init__.py
jig/visualizer/module_dependency/domain/__init__.py
jig/visualizer/module_dependency/domain/model/__init__.py
jig/visualizer/module_dependency/domain/model/graph.py
jig/visualizer/module_dependency/domain/model/graph_style.py
jig/visualizer/module_dependency/domain/model/master_graph.py
jig/visualizer/module_dependency/domain/value/__init__.py
jig/visualizer/module_dependency/domain/value/cluster.py
jig/visualizer/module_dependency/domain/value/edge_style.py
jig/visualizer/module_dependency/domain/value/module_edge.py
jig/visualizer/module_dependency/domain/value/module_edge_style.py
jig/visualizer/module_dependency/domain/value/module_node.py
jig/visualizer/module_dependency/domain/value/module_node_adjacent.py
jig/visualizer/module_dependency/domain/value/module_node_style.py
jig_py-0.1.1.dist-info/LICENSE
jig_py-0.1.1.dist-info/METADATA
jig_py-0.1.1.dist-info/WHEEL
jig_py-0.1.1.dist-info/entry_points.txt
jig_py-0.1.1.dist-info/top_level.txt
jig_py-0.1.1.dist-info/RECORD
